[
  {
    "description": "",
    "elements": [
      {
        "description": "",
        "id": "login-page-testing;login-fails-with-an-invalid-email-(negative-test)",
        "keyword": "Scenario",
        "line": 14,
        "name": "Login fails with an invalid email (negative test)",
        "steps": [
          {
            "keyword": "Before",
            "hidden": true,
            "result": {
              "status": "passed",
              "duration": 882367205
            }
          },
          {
            "arguments": [],
            "keyword": "Given ",
            "line": 15,
            "name": "I am on the login page",
            "match": {
              "location": "src/steps/loginPageTests.ts:9"
            },
            "result": {
              "status": "passed",
              "duration": 3633065721
            }
          },
          {
            "arguments": [],
            "keyword": "When ",
            "line": 16,
            "name": "I enter an invalid email",
            "match": {
              "location": "src/steps/loginPageTests.ts:97"
            },
            "result": {
              "status": "passed",
              "duration": 3032499071
            }
          },
          {
            "arguments": [],
            "keyword": "And ",
            "line": 17,
            "name": "I enter a valid password",
            "match": {
              "location": "src/steps/loginPageTests.ts:33"
            },
            "result": {
              "status": "passed",
              "duration": 3013786081
            }
          },
          {
            "arguments": [],
            "keyword": "And ",
            "line": 18,
            "name": "I click submit button",
            "match": {
              "location": "src/steps/loginPageTests.ts:43"
            },
            "result": {
              "status": "passed",
              "duration": 3133967999
            }
          },
          {
            "arguments": [],
            "keyword": "Then ",
            "line": 19,
            "name": "I should see an error message",
            "match": {
              "location": "src/steps/loginPageTests.ts:103"
            },
            "result": {
              "status": "passed",
              "duration": 3007353371
            }
          },
          {
            "arguments": [],
            "keyword": "And ",
            "line": 20,
            "name": "I should remain on the login page",
            "match": {
              "location": "src/steps/loginPageTests.ts:111"
            },
            "result": {
              "status": "passed",
              "duration": 3002845860
            }
          },
          {
            "keyword": "After",
            "hidden": true,
            "result": {
              "status": "passed",
              "duration": 25997434
            }
          }
        ],
        "tags": [],
        "type": "scenario"
      },
      {
        "description": "",
        "id": "login-page-testing;successful-login-with-\"remember-me\"-checked",
        "keyword": "Scenario",
        "line": 3,
        "name": "Successful login with \"Remember Me\" checked",
        "steps": [
          {
            "keyword": "Before",
            "hidden": true,
            "result": {
              "status": "passed",
              "duration": 103627907
            }
          },
          {
            "arguments": [],
            "keyword": "Given ",
            "line": 4,
            "name": "I am on the login page",
            "match": {
              "location": "src/steps/loginPageTests.ts:9"
            },
            "result": {
              "status": "passed",
              "duration": 3543227894
            }
          },
          {
            "arguments": [],
            "keyword": "When ",
            "line": 5,
            "name": "I enter a valid email",
            "match": {
              "location": "src/steps/loginPageTests.ts:28"
            },
            "result": {
              "status": "passed",
              "duration": 3026165628
            }
          },
          {
            "arguments": [],
            "keyword": "And ",
            "line": 6,
            "name": "I enter a valid password",
            "match": {
              "location": "src/steps/loginPageTests.ts:33"
            },
            "result": {
              "status": "passed",
              "duration": 3010653595
            }
          },
          {
            "arguments": [],
            "keyword": "And ",
            "line": 7,
            "name": "I check keep me signed in checkbox",
            "match": {
              "location": "src/steps/loginPageTests.ts:79"
            },
            "result": {
              "status": "passed",
              "duration": 3036848603
            }
          },
          {
            "arguments": [],
            "keyword": "And ",
            "line": 8,
            "name": "I click submit button",
            "match": {
              "location": "src/steps/loginPageTests.ts:43"
            },
            "result": {
              "status": "passed",
              "duration": 3034706317
            }
          },
          {
            "arguments": [],
            "keyword": "When ",
            "line": 9,
            "name": "I enter valid MFA code on MFA page",
            "match": {
              "location": "src/steps/loginPageTests.ts:14"
            },
            "result": {
              "status": "passed",
              "duration": 6050795638
            }
          },
          {
            "arguments": [],
            "keyword": "Then ",
            "line": 10,
            "name": "I should be logged into the application successfully",
            "match": {
              "location": "src/steps/loginPageTests.ts:48"
            },
            "result": {
              "status": "failed",
              "duration": 8001317295,
              "error_message": "Error: Timed out 5000ms waiting for expect(locator).toHaveTitle(expected)\n\nLocator: locator(':root')\nExpected string: \"Get started | NinjaOne\"\nReceived string: \"NinjaOne\"\nCall log:\n  - locator._expect with timeout 5000ms\n  - waiting for locator(':root')\n    9 × locator resolved to <html lang=\"en\">…</html>\n      - unexpected value \"NinjaOne\"\n\n    at Proxy.<anonymous> (/home/runner/work/NinjaOne/NinjaOne/node_modules/playwright/lib/matchers/expect.js:227:37)\n    at CustomWorld.<anonymous> (/home/runner/work/NinjaOne/NinjaOne/src/steps/loginPageTests.ts:50:29)"
            }
          },
          {
            "arguments": [],
            "keyword": "When ",
            "line": 11,
            "name": "I close and open browser",
            "match": {
              "location": "src/steps/loginPageTests.ts:84"
            },
            "result": {
              "status": "skipped",
              "duration": 0
            }
          },
          {
            "arguments": [],
            "keyword": "And ",
            "line": 12,
            "name": "I should remain logged in after closing and reopening the browser",
            "match": {
              "location": "src/steps/loginPageTests.ts:91"
            },
            "result": {
              "status": "skipped",
              "duration": 0
            }
          },
          {
            "keyword": "After",
            "hidden": true,
            "result": {
              "status": "passed",
              "duration": 109229164
            }
          }
        ],
        "tags": [],
        "type": "scenario"
      },
      {
        "description": "",
        "id": "login-page-testing;successful-login-with-valid-email-and-password",
        "keyword": "Scenario",
        "line": 22,
        "name": "Successful login with valid email and password",
        "steps": [
          {
            "keyword": "Before",
            "hidden": true,
            "result": {
              "status": "passed",
              "duration": 100866813
            }
          },
          {
            "arguments": [],
            "keyword": "Given ",
            "line": 23,
            "name": "I am on the login page",
            "match": {
              "location": "src/steps/loginPageTests.ts:9"
            },
            "result": {
              "status": "passed",
              "duration": 3552513556
            }
          },
          {
            "arguments": [],
            "keyword": "When ",
            "line": 24,
            "name": "I enter a valid email",
            "match": {
              "location": "src/steps/loginPageTests.ts:28"
            },
            "result": {
              "status": "passed",
              "duration": 3030317006
            }
          },
          {
            "arguments": [],
            "keyword": "And ",
            "line": 25,
            "name": "I enter a valid password",
            "match": {
              "location": "src/steps/loginPageTests.ts:33"
            },
            "result": {
              "status": "passed",
              "duration": 3008598417
            }
          },
          {
            "arguments": [],
            "keyword": "And ",
            "line": 26,
            "name": "I click submit button",
            "match": {
              "location": "src/steps/loginPageTests.ts:43"
            },
            "result": {
              "status": "passed",
              "duration": 3049510248
            }
          },
          {
            "arguments": [],
            "keyword": "When ",
            "line": 27,
            "name": "I enter valid MFA code on MFA page",
            "match": {
              "location": "src/steps/loginPageTests.ts:14"
            },
            "result": {
              "status": "passed",
              "duration": 9048617490
            }
          },
          {
            "arguments": [],
            "keyword": "Then ",
            "line": 28,
            "name": "I should be logged into the application successfully",
            "match": {
              "location": "src/steps/loginPageTests.ts:48"
            },
            "result": {
              "status": "failed",
              "duration": 8002914745,
              "error_message": "Error: Timed out 5000ms waiting for expect(locator).toHaveTitle(expected)\n\nLocator: locator(':root')\nExpected string: \"Get started | NinjaOne\"\nReceived string: \"NinjaOne\"\nCall log:\n  - locator._expect with timeout 5000ms\n  - waiting for locator(':root')\n    9 × locator resolved to <html lang=\"en\">…</html>\n      - unexpected value \"NinjaOne\"\n\n    at Proxy.<anonymous> (/home/runner/work/NinjaOne/NinjaOne/node_modules/playwright/lib/matchers/expect.js:227:37)\n    at CustomWorld.<anonymous> (/home/runner/work/NinjaOne/NinjaOne/src/steps/loginPageTests.ts:50:29)"
            }
          },
          {
            "keyword": "After",
            "hidden": true,
            "result": {
              "status": "passed",
              "duration": 100507712
            }
          }
        ],
        "tags": [],
        "type": "scenario"
      },
      {
        "description": "",
        "id": "login-page-testing;succesful-reset-password-with-valid-email",
        "keyword": "Scenario",
        "line": 30,
        "name": "Succesful reset password with valid email",
        "steps": [
          {
            "keyword": "Before",
            "hidden": true,
            "result": {
              "status": "passed",
              "duration": 95318803
            }
          },
          {
            "arguments": [],
            "keyword": "Given ",
            "line": 31,
            "name": "I am on the login page",
            "match": {
              "location": "src/steps/loginPageTests.ts:9"
            },
            "result": {
              "status": "passed",
              "duration": 3542609316
            }
          },
          {
            "arguments": [],
            "keyword": "When ",
            "line": 32,
            "name": "I click the forgot your password link",
            "match": {
              "location": "src/steps/loginPageTests.ts:117"
            },
            "result": {
              "status": "passed",
              "duration": 3056170255
            }
          },
          {
            "arguments": [],
            "keyword": "And ",
            "line": 33,
            "name": "I choose email as a way of verification",
            "match": {
              "location": "src/steps/loginPageTests.ts:123"
            },
            "result": {
              "status": "passed",
              "duration": 3067328901
            }
          },
          {
            "arguments": [],
            "keyword": "Then ",
            "line": 34,
            "name": "I enter a valid email address",
            "match": {
              "location": "src/steps/loginPageTests.ts:129"
            },
            "result": {
              "status": "passed",
              "duration": 3013311571
            }
          },
          {
            "arguments": [],
            "keyword": "And ",
            "line": 35,
            "name": "I click the send button",
            "match": {
              "location": "src/steps/loginPageTests.ts:134"
            },
            "result": {
              "status": "passed",
              "duration": 3074502831
            }
          },
          {
            "arguments": [],
            "keyword": "Then ",
            "line": 36,
            "name": "I should see a confirmation message",
            "match": {
              "location": "src/steps/loginPageTests.ts:139"
            },
            "result": {
              "status": "passed",
              "duration": 3005525389
            }
          },
          {
            "keyword": "After",
            "hidden": true,
            "result": {
              "status": "passed",
              "duration": 22012141
            }
          }
        ],
        "tags": [],
        "type": "scenario"
      }
    ],
    "id": "login-page-testing",
    "line": 1,
    "keyword": "Feature",
    "name": "Login Page Testing",
    "tags": [],
    "uri": "src/features/loginPage.feature"
  }
]