[
  {
    "description": "",
    "elements": [
      {
        "description": "",
        "id": "login-page-testing;successful-account-creation",
        "keyword": "Scenario",
        "line": 3,
        "name": "Successful account creation",
        "steps": [
          {
            "keyword": "Before",
            "hidden": true,
            "result": {
              "status": "passed",
              "duration": 2695600833
            }
          },
          {
            "arguments": [],
            "keyword": "Given ",
            "line": 4,
            "name": "I am on the login page",
            "match": {
              "location": "src/steps/loginPageTests.ts:9"
            },
            "result": {
              "status": "passed",
              "duration": 4752774667
            }
          },
          {
            "arguments": [],
            "keyword": "When ",
            "line": 5,
            "name": "I click create account link",
            "match": {
              "location": "src/steps/loginPageTests.ts:46"
            },
            "result": {
              "status": "passed",
              "duration": 3157599125
            }
          },
          {
            "arguments": [],
            "keyword": "And ",
            "line": 6,
            "name": "I enter all details in form",
            "match": {
              "location": "src/steps/loginPageTests.ts:50"
            },
            "result": {
              "status": "passed",
              "duration": 125486666
            }
          },
          {
            "arguments": [],
            "keyword": "Then ",
            "line": 7,
            "name": "I see account creation message on next page",
            "match": {
              "location": "src/steps/loginPageTests.ts:63"
            },
            "result": {
              "status": "passed",
              "duration": 3015491625
            }
          },
          {
            "keyword": "After",
            "hidden": true,
            "result": {
              "status": "passed",
              "duration": 107426959
            }
          }
        ],
        "tags": [],
        "type": "scenario"
      },
      {
        "description": "",
        "id": "login-page-testing;successful-login-with-\"remember-me\"-checked",
        "keyword": "Scenario",
        "line": 9,
        "name": "Successful login with \"Remember Me\" checked",
        "steps": [
          {
            "keyword": "Before",
            "hidden": true,
            "result": {
              "status": "passed",
              "duration": 2693495791
            }
          },
          {
            "arguments": [],
            "keyword": "Given ",
            "line": 10,
            "name": "I am on the login page",
            "match": {
              "location": "src/steps/loginPageTests.ts:9"
            },
            "result": {
              "status": "passed",
              "duration": 4752073957
            }
          },
          {
            "arguments": [],
            "keyword": "When ",
            "line": 11,
            "name": "I enter a valid email",
            "match": {
              "location": "src/steps/loginPageTests.ts:26"
            },
            "result": {
              "status": "passed",
              "duration": 3057477333
            }
          },
          {
            "arguments": [],
            "keyword": "And ",
            "line": 12,
            "name": "I enter a valid password",
            "match": {
              "location": "src/steps/loginPageTests.ts:30"
            },
            "result": {
              "status": "passed",
              "duration": 3014196000
            }
          },
          {
            "arguments": [],
            "keyword": "And ",
            "line": 13,
            "name": "I check keep me signed in checkbox",
            "match": {
              "location": "src/steps/loginPageTests.ts:68"
            },
            "result": {
              "status": "passed",
              "duration": 3077298916
            }
          },
          {
            "arguments": [],
            "keyword": "And ",
            "line": 14,
            "name": "I click submit button",
            "match": {
              "location": "src/steps/loginPageTests.ts:38"
            },
            "result": {
              "status": "passed",
              "duration": 3055962583
            }
          },
          {
            "arguments": [],
            "keyword": "When ",
            "line": 15,
            "name": "I enter valid MFA code on MFA page",
            "match": {
              "location": "src/steps/loginPageTests.ts:13"
            },
            "result": {
              "status": "passed",
              "duration": 9078026958
            }
          },
          {
            "arguments": [],
            "keyword": "Then ",
            "line": 16,
            "name": "I should be logged into the application successfully",
            "match": {
              "location": "src/steps/loginPageTests.ts:42"
            },
            "result": {
              "status": "passed",
              "duration": 3039275500
            }
          },
          {
            "arguments": [],
            "keyword": "When ",
            "line": 17,
            "name": "I close and open browser",
            "match": {
              "location": "src/steps/loginPageTests.ts:72"
            },
            "result": {
              "status": "passed",
              "duration": 3069686792
            }
          },
          {
            "arguments": [],
            "keyword": "And ",
            "line": 18,
            "name": "I should remain logged in after closing and reopening the browser",
            "match": {
              "location": "src/steps/loginPageTests.ts:78"
            },
            "result": {
              "status": "passed",
              "duration": 3024088458
            }
          },
          {
            "keyword": "After",
            "hidden": true,
            "result": {
              "status": "passed",
              "duration": 98526624
            }
          }
        ],
        "tags": [],
        "type": "scenario"
      },
      {
        "description": "",
        "id": "login-page-testing;login-fails-with-an-invalid-email",
        "keyword": "Scenario",
        "line": 20,
        "name": "Login fails with an invalid email",
        "steps": [
          {
            "keyword": "Before",
            "hidden": true,
            "result": {
              "status": "passed",
              "duration": 746766166
            }
          },
          {
            "arguments": [],
            "keyword": "Given ",
            "line": 21,
            "name": "I am on the login page",
            "match": {
              "location": "src/steps/loginPageTests.ts:9"
            },
            "result": {
              "status": "passed",
              "duration": 4695444333
            }
          },
          {
            "arguments": [],
            "keyword": "When ",
            "line": 22,
            "name": "I enter an invalid email",
            "match": {
              "location": "src/steps/loginPageTests.ts:82"
            },
            "result": {
              "status": "passed",
              "duration": 3048497874
            }
          },
          {
            "arguments": [],
            "keyword": "And ",
            "line": 23,
            "name": "I enter a valid password",
            "match": {
              "location": "src/steps/loginPageTests.ts:30"
            },
            "result": {
              "status": "passed",
              "duration": 3079637959
            }
          },
          {
            "arguments": [],
            "keyword": "And ",
            "line": 24,
            "name": "I click submit button",
            "match": {
              "location": "src/steps/loginPageTests.ts:38"
            },
            "result": {
              "status": "passed",
              "duration": 3060069916
            }
          },
          {
            "arguments": [],
            "keyword": "Then ",
            "line": 25,
            "name": "I should see an error message",
            "match": {
              "location": "src/steps/loginPageTests.ts:86"
            },
            "result": {
              "status": "passed",
              "duration": 3008145333
            }
          },
          {
            "arguments": [],
            "keyword": "And ",
            "line": 26,
            "name": "I should remain on the login page",
            "match": {
              "location": "src/steps/loginPageTests.ts:93"
            },
            "result": {
              "status": "passed",
              "duration": 3017858415
            }
          },
          {
            "keyword": "After",
            "hidden": true,
            "result": {
              "status": "passed",
              "duration": 136399458
            }
          }
        ],
        "tags": [],
        "type": "scenario"
      },
      {
        "description": "",
        "id": "login-page-testing;successful-login-with-valid-email-and-password",
        "keyword": "Scenario",
        "line": 28,
        "name": "Successful login with valid email and password",
        "steps": [
          {
            "keyword": "Before",
            "hidden": true,
            "result": {
              "status": "passed",
              "duration": 788106333
            }
          },
          {
            "arguments": [],
            "keyword": "Given ",
            "line": 29,
            "name": "I am on the login page",
            "match": {
              "location": "src/steps/loginPageTests.ts:9"
            },
            "result": {
              "status": "passed",
              "duration": 4677786582
            }
          },
          {
            "arguments": [],
            "keyword": "When ",
            "line": 30,
            "name": "I enter a valid email",
            "match": {
              "location": "src/steps/loginPageTests.ts:26"
            },
            "result": {
              "status": "passed",
              "duration": 3068212125
            }
          },
          {
            "arguments": [],
            "keyword": "And ",
            "line": 31,
            "name": "I enter a valid password",
            "match": {
              "location": "src/steps/loginPageTests.ts:30"
            },
            "result": {
              "status": "passed",
              "duration": 3017396999
            }
          },
          {
            "arguments": [],
            "keyword": "And ",
            "line": 32,
            "name": "I click submit button",
            "match": {
              "location": "src/steps/loginPageTests.ts:38"
            },
            "result": {
              "status": "passed",
              "duration": 3058898124
            }
          },
          {
            "arguments": [],
            "keyword": "When ",
            "line": 33,
            "name": "I enter valid MFA code on MFA page",
            "match": {
              "location": "src/steps/loginPageTests.ts:13"
            },
            "result": {
              "status": "passed",
              "duration": 9112311041
            }
          },
          {
            "arguments": [],
            "keyword": "Then ",
            "line": 34,
            "name": "I should be logged into the application successfully",
            "match": {
              "location": "src/steps/loginPageTests.ts:42"
            },
            "result": {
              "status": "passed",
              "duration": 3900659291
            }
          },
          {
            "keyword": "After",
            "hidden": true,
            "result": {
              "status": "passed",
              "duration": 88849625
            }
          }
        ],
        "tags": [],
        "type": "scenario"
      },
      {
        "description": "",
        "id": "login-page-testing;reset-password-with-valid-email",
        "keyword": "Scenario",
        "line": 36,
        "name": "Reset password with valid email",
        "steps": [
          {
            "keyword": "Before",
            "hidden": true,
            "result": {
              "status": "passed",
              "duration": 528984791
            }
          },
          {
            "arguments": [],
            "keyword": "Given ",
            "line": 37,
            "name": "I am on the login page",
            "match": {
              "location": "src/steps/loginPageTests.ts:9"
            },
            "result": {
              "status": "passed",
              "duration": 4690708291
            }
          },
          {
            "arguments": [],
            "keyword": "When ",
            "line": 38,
            "name": "I click the forgot your password link",
            "match": {
              "location": "src/steps/loginPageTests.ts:98"
            },
            "result": {
              "status": "passed",
              "duration": 3142920625
            }
          },
          {
            "arguments": [],
            "keyword": "And ",
            "line": 39,
            "name": "I choose email as a way of verification",
            "match": {
              "location": "src/steps/loginPageTests.ts:102"
            },
            "result": {
              "status": "passed",
              "duration": 3091430958
            }
          },
          {
            "arguments": [],
            "keyword": "Then ",
            "line": 40,
            "name": "I enter a valid email address",
            "match": {
              "location": "src/steps/loginPageTests.ts:106"
            },
            "result": {
              "status": "passed",
              "duration": 3029986375
            }
          },
          {
            "arguments": [],
            "keyword": "And ",
            "line": 41,
            "name": "I click the send button",
            "match": {
              "location": "src/steps/loginPageTests.ts:110"
            },
            "result": {
              "status": "passed",
              "duration": 3070125624
            }
          },
          {
            "arguments": [],
            "keyword": "Then ",
            "line": 42,
            "name": "I should see a confirmation message",
            "match": {
              "location": "src/steps/loginPageTests.ts:114"
            },
            "result": {
              "status": "passed",
              "duration": 3015742415
            }
          },
          {
            "keyword": "After",
            "hidden": true,
            "result": {
              "status": "passed",
              "duration": 77466624
            }
          }
        ],
        "tags": [],
        "type": "scenario"
      }
    ],
    "id": "login-page-testing",
    "line": 1,
    "keyword": "Feature",
    "name": "Login Page Testing",
    "tags": [],
    "uri": "src/features/loginPage.feature"
  }
]